Metadata-Version: 2.1
Name: pkgSimran
Version: 0.10.0
Summary: Package to detect secret information from given dataset like KEY_,SECRET_KEY etc
Home-page: UNKNOWN
Author: Simran
Author-email: simran.saxena@dataverze.in
License: UNKNOWN
Platform: UNKNOWN
Classifier: Programming Language :: Python :: 3
Requires-Python: >=3.7
